odoo10_addon_product_pricelist_tier-10.0.1.0.0-py2.7-nspkg.pth
odoo/addons/product_pricelist_tier/README.rst
odoo/addons/product_pricelist_tier/__init__.py
odoo/addons/product_pricelist_tier/__manifest__.py
odoo/addons/product_pricelist_tier/hooks.py
odoo/addons/product_pricelist_tier/demo/product_pricelist_item_demo.xml
odoo/addons/product_pricelist_tier/demo/product_template_demo.xml
odoo/addons/product_pricelist_tier/models/__init__.py
odoo/addons/product_pricelist_tier/models/product_pricelist_item.py
odoo/addons/product_pricelist_tier/static/description/icon.png
odoo/addons/product_pricelist_tier/tests/__init__.py
odoo/addons/product_pricelist_tier/tests/test_hooks.py
odoo/addons/product_pricelist_tier/tests/test_product_pricelist_item.py
odoo/addons/product_pricelist_tier/views/product_pricelist_item_view.xml
odoo10_addon_product_pricelist_tier-10.0.1.0.0.dist-info/DESCRIPTION.rst
odoo10_addon_product_pricelist_tier-10.0.1.0.0.dist-info/METADATA
odoo10_addon_product_pricelist_tier-10.0.1.0.0.dist-info/RECORD
odoo10_addon_product_pricelist_tier-10.0.1.0.0.dist-info/WHEEL
odoo10_addon_product_pricelist_tier-10.0.1.0.0.dist-info/metadata.json
odoo10_addon_product_pricelist_tier-10.0.1.0.0.dist-info/namespace_packages.txt
odoo10_addon_product_pricelist_tier-10.0.1.0.0.dist-info/top_level.txt
